multiword_anagram_fast-0.1.0.2.dist-info/METADATA
multiword_anagram_fast-0.1.0.2.dist-info/WHEEL
multiword_anagram_fast/README.md
multiword_anagram_fast/__init__.py
multiword_anagram_fast/core.cpython-39-s390x-linux-gnu.so
multiword_anagram_fast/dictionaries/ACDLC0A.txt
multiword_anagram_fast/dictionaries/UKACD_LICENSE.txt
multiword_anagram_fast/main.py
multiword_anagram_fast/solver.py
multiword_anagram_fast/tests/test_solver.py
multiword_anagram_fast-0.1.0.2.dist-info/RECORD
