Metadata-Version: 2.4
Name: multiword_anagram_fast
Version: 0.1.0.2
Classifier: Programming Language :: Rust
Classifier: Programming Language :: Python :: Implementation :: CPython
Classifier: Programming Language :: Python :: Implementation :: PyPy
Requires-Dist: maturin>=1.8.6
Summary: Fast multiword anagram solver.
Requires-Python: >=3.7
